convertdate-stubs/METADATA.toml
convertdate-stubs/__init__.pyi
convertdate-stubs/armenian.pyi
convertdate-stubs/bahai.pyi
convertdate-stubs/coptic.pyi
convertdate-stubs/daycount.pyi
convertdate-stubs/dublin.pyi
convertdate-stubs/french_republican.pyi
convertdate-stubs/gregorian.pyi
convertdate-stubs/hebrew.pyi
convertdate-stubs/holidays.pyi
convertdate-stubs/indian_civil.pyi
convertdate-stubs/islamic.pyi
convertdate-stubs/iso.pyi
convertdate-stubs/julian.pyi
convertdate-stubs/julianday.pyi
convertdate-stubs/mayan.pyi
convertdate-stubs/ordinal.pyi
convertdate-stubs/persian.pyi
convertdate-stubs/positivist.pyi
convertdate-stubs/py.typed
convertdate-stubs/utils.pyi
convertdate-stubs/data/__init__.pyi
convertdate-stubs/data/french_republican_days.pyi
convertdate-stubs/data/positivist.pyi
types_convertdate-2.4.0.20250827.dist-info/licenses/LICENSE
types_convertdate-2.4.0.20250827.dist-info/METADATA
types_convertdate-2.4.0.20250827.dist-info/WHEEL
types_convertdate-2.4.0.20250827.dist-info/top_level.txt
types_convertdate-2.4.0.20250827.dist-info/RECORD
